MANIFEST.in
gssapi_ez_setup.py
setup.py
gssapi/__about__.py
gssapi/__init__.py
gssapi/creds.py
gssapi/ctx.py
gssapi/error.py
gssapi/names.py
gssapi/oids.py
gssapi/bindings/__init__.py
gssapi/bindings/cffi_gssapi.cdef
python_gssapi.egg-info/PKG-INFO
python_gssapi.egg-info/SOURCES.txt
python_gssapi.egg-info/dependency_links.txt
python_gssapi.egg-info/not-zip-safe
python_gssapi.egg-info/requires.txt
python_gssapi.egg-info/top_level.txt